lndb_storage/__init__.py
lndb_storage/_file.py
lndb_storage/_h5ad.py
lndb_storage/_images.py
lndb_storage/_subset.py
lndb_storage/_zarr.py
lndb_storage/object/__init__.py
lndb_storage/object/_anndata.py
lndb_storage/object/_anndata_accessor.py
lndb_storage/object/_anndata_sizes.py
lndb_storage/object/_core.py
lndb_storage/object/_lazy_field.py
lndb_storage/object/_subset_anndata.py
lndb_storage-0.3.2.dist-info/LICENSE
lndb_storage-0.3.2.dist-info/WHEEL
lndb_storage-0.3.2.dist-info/METADATA
lndb_storage-0.3.2.dist-info/RECORD
